scikit_tree-0.8.0.dist-info/WHEEL
scikit_tree-0.8.0.dist-info/RECORD
scikit_tree-0.8.0.dist-info/METADATA
sktree/conftest.py
sktree/neighbors.py
sktree/__init__.py
sktree/_lib/sklearn/neighbors/_quad_tree.cpython-310-x86_64-linux-gnu.so
sktree/_lib/sklearn/ensemble/_forest.py
sktree/_lib/sklearn/tree/_classes.py
sktree/_lib/sklearn/tree/_criterion.cpython-310-x86_64-linux-gnu.so
sktree/_lib/sklearn/tree/_export.py
sktree/_lib/sklearn/tree/_utils.cpython-310-x86_64-linux-gnu.so
sktree/_lib/sklearn/tree/__init__.py
sktree/_lib/sklearn/tree/_tree.cpython-310-x86_64-linux-gnu.so
sktree/_lib/sklearn/tree/_splitter.cpython-310-x86_64-linux-gnu.so
sktree/_lib/sklearn/tree/_reingold_tilford.py
sktree/_lib/sklearn/utils/_typedefs.cpython-310-x86_64-linux-gnu.so
sktree/_lib/sklearn/utils/_random.cpython-310-x86_64-linux-gnu.so
sktree/tests/test_extensions.py
sktree/tests/test_unsupervised_forest.py
sktree/tests/test_supervised_forest.py
sktree/tests/test_neighbors.py
sktree/tests/test_eiforest.py
sktree/tests/test_multiview_forest.py
sktree/tests/test_honest_forest.py
sktree/tests/__init__.py
sktree/datasets/multiview.py
sktree/datasets/hyppo.py
sktree/datasets/__init__.py
sktree/datasets/tests/test_hyppo.py
sktree/datasets/tests/test_multiview.py
sktree/datasets/tests/__init__.py
sktree/ensemble/_eiforest.py
sktree/ensemble/_multiview.py
sktree/ensemble/_extensions.py
sktree/ensemble/_supervised_forest.py
sktree/ensemble/_honest_forest.py
sktree/ensemble/_unsupervised_forest.py
sktree/ensemble/__init__.py
sktree/tree/_multiview.py
sktree/tree/_classes.py
sktree/tree/_oblique_splitter.cpython-310-x86_64-linux-gnu.so
sktree/tree/_neighbors.py
sktree/tree/_oblique_tree.cpython-310-x86_64-linux-gnu.so
sktree/tree/_sklearn_splitter.cpython-310-x86_64-linux-gnu.so
sktree/tree/_utils.cpython-310-x86_64-linux-gnu.so
sktree/tree/_marginal.cpython-310-x86_64-linux-gnu.so
sktree/tree/__init__.py
sktree/tree/_honest_tree.py
sktree/tree/_marginalize.py
sktree/tree/manifold/_morf_splitter.cpython-310-x86_64-linux-gnu.so
