Metadata-Version: 2.1
Name: scikit-tree
Version: 0.8.0
Summary: Modern decision trees in Python
Keywords: tree,oblique trees,manifold-learning,scikit-learn
Maintainer-Email: Neurodata <adam.li@columbia.edu>
Classifier: Development Status :: 4 - Beta
Classifier: Intended Audience :: Science/Research
Classifier: Intended Audience :: Developers
Classifier: License :: OSI Approved :: BSD License
Classifier: Programming Language :: C
Classifier: Programming Language :: Python
Classifier: Programming Language :: Python :: 3
Classifier: Programming Language :: Python :: 3.9
Classifier: Programming Language :: Python :: 3.10
Classifier: Programming Language :: Python :: 3.11
Classifier: Programming Language :: Python :: 3.12
Classifier: Topic :: Scientific/Engineering
Classifier: Operating System :: Microsoft :: Windows
Classifier: Operating System :: POSIX :: Linux
Classifier: Operating System :: POSIX
Classifier: Operating System :: Unix
Classifier: Operating System :: MacOS
Requires-Python: >=3.9
Requires-Dist: numpy>=1.25.0
Requires-Dist: scipy>=1.5.0
Requires-Dist: scikit-learn>=1.4.1
Requires-Dist: scikit-tree[build]; extra == "all"
Requires-Dist: scikit-tree[doc]; extra == "all"
Requires-Dist: scikit-tree[style]; extra == "all"
Requires-Dist: scikit-tree[test]; extra == "all"
Requires-Dist: build; extra == "build"
Requires-Dist: twine; extra == "build"
Requires-Dist: meson; extra == "build"
Requires-Dist: meson-python; extra == "build"
Requires-Dist: spin; extra == "build"
Requires-Dist: doit; extra == "build"
Requires-Dist: scikit-learn>=1.5.0; extra == "build"
Requires-Dist: Cython>=3.0.10; extra == "build"
Requires-Dist: ninja; extra == "build"
Requires-Dist: numpy>=1.25.0; extra == "build"
Requires-Dist: rich-click; extra == "build"
Requires-Dist: pydevtool; extra == "build"
Requires-Dist: memory-profiler; extra == "doc"
Requires-Dist: numpydoc; extra == "doc"
Requires-Dist: pooch; extra == "doc"
Requires-Dist: pydata-sphinx-theme==0.14.1; extra == "doc"
Requires-Dist: sphinx==7.2.6; extra == "doc"
Requires-Dist: sphinx-copybutton; extra == "doc"
Requires-Dist: sphinx-design; extra == "doc"
Requires-Dist: sphinx-gallery; extra == "doc"
Requires-Dist: sphinx-issues; extra == "doc"
Requires-Dist: sphinx_autodoc_typehints; extra == "doc"
Requires-Dist: sphinxcontrib-bibtex; extra == "doc"
Requires-Dist: portray; extra == "doc"
Requires-Dist: matplotlib; extra == "doc"
Requires-Dist: ipython; extra == "doc"
Requires-Dist: nbsphinx; extra == "doc"
Requires-Dist: memory_profiler; extra == "doc"
Requires-Dist: pandas; extra == "doc"
Requires-Dist: seaborn; extra == "doc"
Requires-Dist: joblib; extra == "doc"
Requires-Dist: pre-commit; extra == "style"
Requires-Dist: black; extra == "style"
Requires-Dist: codespell; extra == "style"
Requires-Dist: isort; extra == "style"
Requires-Dist: pydocstyle; extra == "style"
Requires-Dist: pydocstyle[toml]; extra == "style"
Requires-Dist: rstcheck; extra == "style"
Requires-Dist: ruff; extra == "style"
Requires-Dist: toml-sort; extra == "style"
Requires-Dist: yamllint; extra == "style"
Requires-Dist: mypy; extra == "style"
Requires-Dist: flake8; extra == "style"
Requires-Dist: bandit; extra == "style"
Requires-Dist: toml; extra == "style"
Requires-Dist: cython-lint; extra == "style"
Requires-Dist: joblib; extra == "test"
Requires-Dist: pandas; extra == "test"
Requires-Dist: pytest; extra == "test"
Requires-Dist: pytest-cov; extra == "test"
Requires-Dist: memory_profiler; extra == "test"
Requires-Dist: flaky; extra == "test"
Requires-Dist: tqdm; extra == "test"
Provides-Extra: all
Provides-Extra: build
Provides-Extra: doc
Provides-Extra: style
Provides-Extra: test
